django_static_jquery_ui/.DS_Store
django_static_jquery_ui/__init__.py
django_static_jquery_ui/models.py
django_static_jquery_ui/migrations/__init__.py
django_static_jquery_ui/static/.DS_Store
django_static_jquery_ui/static/jquery-ui/.DS_Store
django_static_jquery_ui/static/jquery-ui/AUTHORS.txt
django_static_jquery_ui/static/jquery-ui/LICENSE.txt
django_static_jquery_ui/static/jquery-ui/index.html
django_static_jquery_ui/static/jquery-ui/jquery-ui.css
django_static_jquery_ui/static/jquery-ui/jquery-ui.js
django_static_jquery_ui/static/jquery-ui/jquery-ui.min.css
django_static_jquery_ui/static/jquery-ui/jquery-ui.min.js
django_static_jquery_ui/static/jquery-ui/jquery-ui.structure.css
django_static_jquery_ui/static/jquery-ui/jquery-ui.structure.min.css
django_static_jquery_ui/static/jquery-ui/jquery-ui.theme.css
django_static_jquery_ui/static/jquery-ui/jquery-ui.theme.min.css
django_static_jquery_ui/static/jquery-ui/package.json
django_static_jquery_ui/static/jquery-ui/external/jquery/jquery.js
django_static_jquery_ui/static/jquery-ui/i18n/datepicker-ar.js
django_static_jquery_ui/static/jquery-ui/i18n/datepicker-fr.js
django_static_jquery_ui/static/jquery-ui/i18n/datepicker-he.js
django_static_jquery_ui/static/jquery-ui/i18n/datepicker-zh-Hans.js
django_static_jquery_ui/static/jquery-ui/images/ui-icons_444444_256x240.png
django_static_jquery_ui/static/jquery-ui/images/ui-icons_555555_256x240.png
django_static_jquery_ui/static/jquery-ui/images/ui-icons_777620_256x240.png
django_static_jquery_ui/static/jquery-ui/images/ui-icons_777777_256x240.png
django_static_jquery_ui/static/jquery-ui/images/ui-icons_cc0000_256x240.png
django_static_jquery_ui/static/jquery-ui/images/ui-icons_ffffff_256x240.png
django_static_jquery_ui/static/jquery-ui/themes/base/jquery-ui.css
django_static_jquery_ui/static/jquery-ui/themes/base/jquery-ui.min.css
django_static_jquery_ui/static/jquery-ui/themes/base/theme.css
django_static_jquery_ui-1.13.3.2.dist-info/licenses/LICENSE
django_static_jquery_ui-1.13.3.2.dist-info/METADATA
django_static_jquery_ui-1.13.3.2.dist-info/WHEEL
django_static_jquery_ui-1.13.3.2.dist-info/top_level.txt
django_static_jquery_ui-1.13.3.2.dist-info/RECORD
